{
  "BattleResults":  {
    "battleWinLose":  "Lose",
    "battleSettlementIndex":  0,
    "bToBadEnd":  false,
    "playerRecord":  {
      "matchDisconnectionCount":  -1,
      "rank":  1,
      "rankPoint":  0,
      "rankMatchSingleRank":  1,
      "rankMatchSingleRankPoint":  0,
      "rankMatchTeamRank":  1,
      "rankMatchTeamRankPoint":  1,
      "money":  0,
      "eventPoint":  0,
      "playerRatePoint":  0,
      "rewardPoint":  0,
      "battlePassPoint":  0,
      "playTime":  0
    },
    "characterRecord":  {
      "(Key=\"１ＶＳ１の１Ｐの開始地点\")":  {
        "battlePlayCharacter":  {
          "character":  {
            "key":  "0020_00"
          },
          "costume":  {
            "key":  "0020_00_03"
          },
          "sparkingBGM":  {
            "key":  "BGM_M0200"
          },
          "bReplaceCharacterCamera":  false,
          "cameraBlueprint":  "None",
          "sequenceRebindRegexPattern":  "None",
          "equipItem":  [
            {
              "key":  "00_1_0003_0020_00"
            },
            {
              "key":  "00_6_0000"
            },
            {
              "key":  "00_4_0000_0020_00"
            },
            {
              "key":  "00_4_0000_0020_00"
            },
            {
              "key":  "00_4_0000_0020_00"
            },
            {
              "key":  "00_4_0000_0020_00"
            },
            {
              "key":  "00_4_1000_0020_00"
            },
            {
              "key":  "00_4_1000_0020_00"
            },
            {
              "key":  "00_4_1000_0020_00"
            },
            {
              "key":  "00_4_1000_0020_00"
            },
            {
              "key":  "00_0_0005"
            },
            {
              "key":  "00_7_0001"
            }
          ],
          "itemSaveState":  {
          },
          "battleControlMode":  "Com",
          "bKnockDown":  true,
          "bBlowIsFront":  false,
          "bRingOut":  false,
          "bFusionPotara":  false,
          "hPGaugeValue":  0,
          "hPGaugeValueMax":  40000,
          "sPGaugeValue":  27801.875,
          "blastStockCount":  3,
          "blastGaugeValue":  0.59314060211181641,
          "nextSkillGaugeGainHP":  -10000,
          "bDoneLastOneHPSkillGaugeGain":  true,
          "addMaxHP":  0,
          "cpuLevel":  11,
          "cpuThinkingType":  {
            "key":  "タイプ２"
          },
          "battlePlayLevel":  [
          ],
          "battlePlayEasy":  {
            "equipItem":  [
            ],
            "cpuLevel":  -1
          },
          "battlePlayOrb":  {
            "equipItem":  [
            ],
            "cpuLevel":  -1
          },
          "battlePlayOrbEasy":  {
            "equipItem":  [
            ],
            "cpuLevel":  -1
          },
          "costumeDamageLv":  3,
          "costumeScratchLv":  1,
          "originalCharacter":  {
            "key":  "0020_00"
          },
          "changedStates":  [
            "CostumeDamaged",
            "NoHit_RushCombatives",
            "NoHit_RushEnergyBullet",
            "Damage",
            "GuardedDamage",
            "Sparking",
            "NoHit_Combatives",
            "NoHit_SpeedImpactTrigger",
            "SparkingEnd",
            "NoHit_BlastForte2",
            "NoHit_CrashImpactTrigger",
            "NoHit_SmashCombatives",
            "KnockDown"
          ],
          "preChangedStates":  [
          ]
        },
        "battleCount":  {
          "maxComboNum":  22,
          "maxComboDamage":  13063,
          "killCount":  0,
          "givenDamage":  29041,
          "takenDamage":  45287,
          "battleTime":  "+00000000.00:02:50.440000000",
          "battleNumCount":  {
            "specialFatePreBattleProduction":  1,
            "vanishingAttack":  1,
            "shotEnergyBulletCount":  41,
            "chargeCount":  8,
            "reflectEnergyBulletCount":  11,
            "guardCount":  10,
            "sparkingCount":  3,
            "zCounter":  1,
            "uLTCount":  1,
            "sparkingCombo":  1,
            "eXACount":  3
          },
          "useBlastGroupCount":  {
            "(Key=\"GR0020_00UB\")":  1
          },
          "attackHitCount":  {
            "(Key=\"actRSHA2\")":  7,
            "(Key=\"actRSHA1\")":  4,
            "(Key=\"actFLK\")":  3,
            "(Key=\"actFLKF\")":  1,
            "(Key=\"actRSHB1\")":  1,
            "(Key=\"actRSHB2\")":  1,
            "(Key=\"actRSHB3\")":  1,
            "(Key=\"actRSHB4\")":  1,
            "(Key=\"actRSHB5\")":  1,
            "(Key=\"actRI1\")":  1,
            "(Key=\"actRI2\")":  1,
            "(Key=\"actVAAD\")":  1,
            "(Key=\"actRSB\")":  6,
            "(Key=\"actVASN\")":  1,
            "(Key=\"actZCOL\")":  1,
            "(Key=\"actULTSI\")":  1,
            "(Key=\"actULTHD1P\")":  21,
            "(Key=\"actULTHI\")":  1,
            "(Key=\"actBLWF\")":  1,
            "(Key=\"actRSHA3\")":  1,
            "(Key=\"actRSHA4\")":  1,
            "(Key=\"actRSHA5\")":  1
          },
          "runBlastCount":  {
            "(Key=\"ULT\")":  1,
            "(Key=\"EXA2\")":  2,
            "(Key=\"EXA1\")":  1
          },
          "blastHitDemoInfo":  {
            "(BlastAction=(Key=\"ULT\"),TargetCharacter=(Key=\"0030_00\"))":  1
          },
          "throwFinishInfo":  {
          },
          "runEmoteCount":  {
          },
          "dragonDashMileage":  3485.292724609375
        },
        "formChangeHistory":  [
        ]
      },
      "(Key=\"１ＶＳ１の２Ｐの開始地点\")":  {
        "battlePlayCharacter":  {
          "character":  {
            "key":  "0030_00"
          },
          "costume":  {
            "key":  "0030_00_02"
          },
          "sparkingBGM":  {
            "key":  "BGM_M0200"
          },
          "bReplaceCharacterCamera":  false,
          "cameraBlueprint":  "None",
          "sequenceRebindRegexPattern":  "None",
          "equipItem":  [
            {
              "key":  "00_1_0002_0030_00"
            },
            {
              "key":  "00_6_0000"
            },
            {
              "key":  "00_4_0008"
            },
            {
              "key":  "00_4_0008"
            },
            {
              "key":  "00_4_0008"
            },
            {
              "key":  "00_4_0008"
            },
            {
              "key":  "00_4_1000_0030_00"
            },
            {
              "key":  "00_4_1000_0030_00"
            },
            {
              "key":  "00_4_1000_0030_00"
            },
            {
              "key":  "00_4_1000_0030_00"
            },
            {
              "key":  "00_0_0028"
            },
            {
              "key":  "00_7_0002"
            }
          ],
          "itemSaveState":  {
          },
          "battleControlMode":  "Com",
          "bKnockDown":  false,
          "bBlowIsFront":  false,
          "bRingOut":  false,
          "bFusionPotara":  false,
          "hPGaugeValue":  10959,
          "hPGaugeValueMax":  40000,
          "sPGaugeValue":  12960.25,
          "blastStockCount":  2,
          "blastGaugeValue":  0.94097620248794556,
          "nextSkillGaugeGainHP":  10000,
          "bDoneLastOneHPSkillGaugeGain":  false,
          "addMaxHP":  0,
          "cpuLevel":  11,
          "cpuThinkingType":  {
            "key":  "タイプ３"
          },
          "battlePlayLevel":  [
          ],
          "battlePlayEasy":  {
            "equipItem":  [
            ],
            "cpuLevel":  -1
          },
          "battlePlayOrb":  {
            "equipItem":  [
            ],
            "cpuLevel":  -1
          },
          "battlePlayOrbEasy":  {
            "equipItem":  [
            ],
            "cpuLevel":  -1
          },
          "costumeDamageLv":  3,
          "costumeScratchLv":  1,
          "originalCharacter":  {
            "key":  "0030_00"
          },
          "changedStates":  [
            "CostumeDamaged",
            "Damage",
            "NoHit_RushCombatives",
            "NoHit_RushEnergyBullet",
            "NoHit_Combatives",
            "Sparking",
            "NoHit_PowerImpactTrigger",
            "SparkingEnd",
            "NoHit_SmashEnergyBullet",
            "NoHit_BlastForte1",
            "GuardedDamage",
            "NoHit_SpeedImpactTrigger",
            "NoHit_BlastImpactTrigger",
            "NoHit_CrashImpactTrigger"
          ],
          "preChangedStates":  [
          ]
        },
        "battleCount":  {
          "maxComboNum":  41,
          "maxComboDamage":  19007,
          "killCount":  1,
          "givenDamage":  45287,
          "takenDamage":  29041,
          "battleTime":  "+00000000.00:02:50.440000000",
          "battleNumCount":  {
            "specialFatePreBattleProduction":  1,
            "guardCount":  6,
            "chargeCount":  7,
            "reflectEnergyBulletCount":  9,
            "shotEnergyBulletCount":  31,
            "sparkingCount":  5,
            "throwCount":  2,
            "zCounter":  1,
            "eXACount":  1,
            "uLTCount":  1,
            "sPMCount":  1,
            "superCounterCount":  1
          },
          "useBlastGroupCount":  {
            "(Key=\"GR0030_00UB\")":  1,
            "(Key=\"GR0030_00B1\")":  1
          },
          "attackHitCount":  {
            "(Key=\"actBLWF\")":  1,
            "(Key=\"actSTDSMBN\")":  2,
            "(Key=\"actRSB\")":  9,
            "(Key=\"actRSHA1\")":  5,
            "(Key=\"actRSHA2\")":  5,
            "(Key=\"actRSHA3\")":  3,
            "(Key=\"actRSHA4\")":  3,
            "(Key=\"actVASN\")":  3,
            "(Key=\"actTRW\")":  2,
            "(Key=\"actTRW1P\")":  14,
            "(Key=\"actTRWFT\")":  2,
            "(Key=\"actBSA\")":  2,
            "(Key=\"actSCN\")":  1,
            "(Key=\"actVASF\")":  1,
            "(Key=\"actRSHA5\")":  2,
            "(Key=\"actRI1\")":  1,
            "(Key=\"actRI2\")":  1,
            "(Key=\"actDDS\")":  3,
            "(Key=\"actBSM1\")":  1,
            "(Key=\"actLTAC\")":  1,
            "(Key=\"actLTAOT\")":  1,
            "(Key=\"actULTSI\")":  1,
            "(Key=\"actULTHD1P\")":  40,
            "(Key=\"actULTHI\")":  1,
            "(Key=\"actSPM1SI\")":  5,
            "(Key=\"actZCBGU\")":  1,
            "(Key=\"actZCBAR\")":  1
          },
          "runBlastCount":  {
            "(Key=\"EXA1\")":  1,
            "(Key=\"ULT\")":  1,
            "(Key=\"SPM1\")":  1
          },
          "blastHitDemoInfo":  {
            "(BlastAction=(Key=\"ULT\"),TargetCharacter=(Key=\"0020_00\"))":  1
          },
          "throwFinishInfo":  {
            "(Key=\"0020_00\")":  2
          },
          "runEmoteCount":  {
          },
          "dragonDashMileage":  10281.9306640625
        },
        "formChangeHistory":  [
        ]
      }
    },
    "originalCharacterIdRecord":  {
    },
    "characterIdRecord":  {
    },
    "mapRecord":  {
      "(Key=\"Map006\")":  {
        "battleCount":  {
          "changeEscapeCount":  0,
          "changeDestructCount":  0
        }
      }
    },
    "originalMap":  {
      "key":  "Map006"
    },
    "isSpConclusion":  false,
    "conclusionEventData":  {
      "eventSceneData":  "None",
      "displayText":  {
        "originalText":  {
          "key":  "None"
        },
        "replaceWord":  {
          "key":  "None"
        },
        "replaceWord2":  {
          "key":  "None"
        }
      },
      "titleImageData":  {
        "key":  "None"
      },
      "bGMData":  {
        "key":  "None"
      },
      "editSceneId":  "None"
    },
    "battleSettleTransitionType":  "KnockOut",
    "bSpecialFatePreBattleProduction":  true,
    "specialFatePreBattleProductionCharacters":  [
      {
        "key":  "0030_00"
      },
      {
        "key":  "0020_00"
      }
    ],
    "bDramaticFinish":  false,
    "battleClearCount":  0,
    "battleAnotherClearCount":  0,
    "bBattleAnotherClear":  false,
    "battleReward":  [
    ],
    "unacquiredMythicalOrb":  [
    ],
    "bResultStart":  true,
    "battleFinishCharacterId":  {
      "key":  "0030_00"
    },
    "battleFinishBlast":  {
      "key":  "None"
    }
  }
}
